{
  "tiers": {
    "tier_1": [
      "University of Oxford", "University of Cambridge", "Imperial College London", "London School of Economics", "LSE", "University College London", "UCL"
    ],
    "tier_2": [
      "University of Warwick", "Durham University", "University of Edinburgh", "University of Manchester", "King's College London", "KCL", "University of Bristol", "University of St Andrews", "University of Bath"
    ],
    "tier_3": [
      "University of Southampton", "University of Birmingham", "University of Sheffield", "University of Leeds", "University of Nottingham", "University of Liverpool", "Queen Mary University of London", "University of Exeter", "University of York", "Cardiff University", "Newcastle University", "Queen's University Belfast"
    ]
  },
  "uk_universities": [
    "University of Oxford", "University of Cambridge", "Imperial College London", "University College London", "UCL", "London School of Economics", "LSE",
    "University of Edinburgh", "University of Manchester", "King's College London", "KCL", "University of Warwick", "University of Bristol", "University of Glasgow",
    "University of Southampton", "University of Birmingham", "University of Sheffield", "University of Leeds", "University of Nottingham", "University of St Andrews",
    "University of Liverpool", "Queen Mary University of London", "University of Exeter", "University of York", "Cardiff University", "Durham University",
    "University of Reading", "University of Sussex", "Loughborough University", "University of Leicester", "University of Surrey", "University of Strathclyde",
    "University of East Anglia", "University of Dundee", "University of Aberdeen", "University of Bath", "Newcastle University", "Swansea University",
    "Queen's University Belfast", "Birkbeck", "City, University of London", "Brunel University London", "Goldsmiths", "Royal Holloway", "SOAS",
    "University of Portsmouth", "University of Plymouth", "University of Greenwich", "University of Hertfordshire", "Northumbria University",
    "University of Central Lancashire", "University of Salford", "University of Huddersfield", "University of Lincoln", "University of Derby",
    "University of Brighton", "University of Roehampton", "University of Westminster", "Kingston University", "Middlesex University", "Coventry University"
  ]
}
